{"stats": [{"N": "Videos", "C": "5"}, {"N": "Songs", "C": "1"}, {"N": "Composers", "C": "1"}, {"N": "Types", "C": "1"}, {"N": "Duration", "C": "44 M"}, {"N": "Views", "C": "2 K"}], "info": [{"N": "Melakartha:", "V": "29 Dheera sankarabharanam"}, {"N": "Arohanam:", "V": "S R2 M1 P D2 N3 S <a href=\"javascript:play_notes('S1 R2 M1 P D2 N3 S2');\" ><img class=\"ICON\" src=\"icons/soundwave.svg\" ></a>"}, {"N": "Avarohanam:", "V": "S D2 P M1 R2 S <a href=\"javascript:play_notes('S2 D2 P M1 R2 S1');\" ><img class=\"ICON\" src=\"icons/soundwave.svg\" ></a>"}], "keyboard": {"P": "Images/carnatic_keyboard.jpg"}, "title": {"N": "Nagabhushani", "I": "music-note-list"}, "videos": [{"folder": [{"H": 9493, "S": 9291, "songs": [{"A": 1258, "C": 2008, "D": "8:26", "I": "GSCK_Y_JnFg", "R": 464, "T": 0, "V": "309"}, {"A": 1256, "C": 2008, "D": "13:11", "I": "BxtlFoDj-Ms", "R": 464, "T": 0, "V": "337"}, {"A": 1256, "C": 2008, "D": "13:11", "I": "I8H1XZpr0gk", "R": 464, "T": 0, "V": "355"}, {"A": 1464, "C": 2008, "D": "5:34", "I": "YnBlbeZbk9E", "R": 464, "T": 0, "V": "279"}, {"A": 1464, "C": 2008, "D": "5:36", "I": "yhsSdi9Z2E0", "R": 464, "T": 0, "V": "14"}]}]}]}