{"stats": [{"N": "Videos", "C": "124"}, {"N": "Songs", "C": "72"}, {"N": "Ragas", "C": "41"}, {"N": "Composers", "C": "16"}, {"N": "Duration", "C": "28 H"}, {"N": "Views", "C": "191 K"}], "poster": {"P": "Images/PBP.jpg"}, "title": {"N": "Parassala B. Ponnammal", "I": "person-fill"}, "videos": [{"folder": [{"H": 10222, "S": 10222, "songs": [{"A": 1154, "C": 2003, "D": "3:47", "I": "PnO9t63SBqY", "R": 113, "T": 0, "V": "181"}]}, {"H": 13803, "S": 13801, "songs": [{"A": 1154, "C": 2079, "D": "7:58", "I": "1KxECj2mw8Y", "R": 123, "T": 22, "V": "136"}]}, {"H": 5878, "S": 5851, "songs": [{"A": 1154, "C": 2002, "D": "13:12", "I": "FBVvO9GdsDw", "R": 140, "T": 0, "V": "1,400"}]}, {"H": 5445, "S": 5446, "songs": [{"A": 1154, "C": 2003, "D": "44:01", "I": "hWoUePfi8-I", "R": 117, "T": 0, "V": "140"}]}, {"H": 5290, "S": 5284, "songs": [{"A": 1154, "C": 2002, "D": "10:05", "I": "m8Ki_r-m1_Q", "R": 103, "T": 0, "V": "60"}]}, {"H": 7200, "S": 7132, "songs": [{"A": 1154, "C": 2003, "D": "51:56", "I": "D56ULXDbiBw", "R": 135, "T": 0, "V": "247"}]}, {"H": 12108, "S": 11291, "songs": [{"A": 1154, "C": 2036, "D": "25:21", "I": "uBEwyAak1m8", "R": 104, "T": 0, "V": "310"}]}, {"H": 5468, "S": 5455, "songs": [{"A": 1154, "C": 2001, "D": "6:50", "I": "GYItxBKfYJg", "R": 123, "T": 0, "V": "925"}, {"A": 1154, "C": 2001, "D": "12:11", "I": "IFt6k_xaNlM", "R": 123, "T": 0, "V": "1,300"}]}, {"H": 9519, "S": 9302, "songs": [{"A": 1154, "C": 2137, "D": "8:49", "I": "Cv_Yv1DTrlw", "R": 183, "T": 0, "V": "23"}, {"A": 1154, "C": 2137, "D": "8:50", "I": "pBvkF8QASFY", "R": 183, "T": 0, "V": "193"}, {"A": 1154, "C": 2137, "D": "5:28", "I": "1YXzhjtBqBY", "R": 183, "T": 0, "V": "733"}]}, {"H": 12082, "S": 11275, "songs": [{"A": 1154, "C": 2003, "D": "5:16", "I": "Hqhzg6-Wbcg", "R": 191, "T": 0, "V": "323"}]}, {"H": 10847, "S": 10493, "songs": [{"A": 1154, "C": 2003, "D": "42:36", "I": "1EQNM-ixKU0", "R": 102, "T": 0, "V": "155"}]}, {"H": 7128, "S": 7128, "songs": [{"A": 1154, "C": 2008, "D": "3:18", "I": "dnddntGqfV4", "R": 149, "T": 24, "V": "1,100"}, {"A": 1154, "C": 2008, "D": "2:59", "I": "aGb2018w3v8", "R": 149, "T": 24, "V": "949"}]}, {"H": 6330, "S": 6329, "songs": [{"A": 1154, "C": 2002, "D": "6:51", "I": "QkWBqcgKxqU", "R": 186, "T": 0, "V": "215"}]}, {"H": 6253, "S": 6221, "songs": [{"A": 1154, "C": 2020, "D": "5:01", "I": "2nc8jArBJII", "R": 129, "T": 0, "V": "1,100"}]}, {"H": 5441, "S": 5432, "songs": [{"A": 1154, "C": 2002, "D": "5:08", "I": "w89uo3HmXA8", "R": 275, "T": 0, "V": "22,000"}, {"A": 1154, "C": 2002, "D": "6:31", "I": "dW2fHEgs3vY", "R": 275, "T": 0, "V": "5"}, {"A": 1154, "C": 2002, "D": "5:05", "I": "frd090YS3hQ", "R": 275, "T": 0, "V": "1,500"}, {"A": 1154, "C": 2002, "D": "5:08", "I": "EZ4nn1ylvHo", "R": 275, "T": 0, "V": "942"}]}, {"H": 6652, "S": 6609, "songs": [{"A": 1154, "C": 2130, "D": "20:09", "I": "Sm87krUPt00", "R": 102, "T": 0, "V": "1,700"}]}, {"H": 5248, "S": 5243, "songs": [{"A": 1154, "C": 2003, "D": "8:12", "I": "i6MIp4Fxp4U", "R": 238, "T": 0, "V": "3,600"}]}, {"H": 7190, "S": 7123, "songs": [{"A": 1154, "C": 2003, "D": "22:06", "I": "3T2kGW7vb1o", "R": 139, "T": 0, "V": "184"}]}, {"H": 6651, "S": 6608, "songs": [{"A": 1154, "C": 2056, "D": "5:50", "I": "7lSpljFj1HA", "R": 106, "T": 0, "V": "424"}]}, {"H": 5193, "S": 5190, "songs": [{"A": 1154, "C": 2001, "D": "17:24", "I": "ukSe70BXi-g", "R": 116, "T": 0, "V": "1,400"}, {"A": 1154, "C": 2001, "D": "7:49", "I": "ni5UB4cYlKs", "R": 116, "T": 0, "V": "1,200"}]}, {"H": 5192, "S": 5189, "songs": [{"A": 1154, "C": 2001, "D": "21:04", "I": "O5OMBj4G4Ek", "R": 102, "T": 0, "V": "16"}]}, {"H": 6198, "S": 6167, "songs": [{"A": 1154, "C": 2006, "D": "14:38", "I": "h4H1SAOMNYQ", "R": 138, "T": 45, "V": "8,800"}]}, {"H": 5822, "S": 5808, "songs": [{"A": 1154, "C": 2003, "D": "7:26", "I": "E0VFs4Cz7FA", "R": 140, "T": 0, "V": "449"}]}, {"H": 5373, "S": 5361, "songs": [{"A": 1154, "C": 2003, "D": "17:54", "I": "iTGy1nFr4rE", "R": 155, "T": 0, "V": "869"}]}, {"H": 5659, "S": 5649, "songs": [{"A": 1154, "C": 2002, "D": "22:59", "I": "OGKFEnVHMxk", "R": 119, "T": 51, "V": "6"}]}, {"H": 11832, "S": 11832, "songs": [{"A": 1154, "C": 2079, "D": "9:26", "I": "ycAJgTOfJ9w", "R": 103, "T": 0, "V": "109"}]}, {"H": 11826, "S": 11127, "songs": [{"A": 1154, "C": 2008, "D": "13:55", "I": "yyyVbpVmrsk", "R": 203, "T": 0, "V": "357"}, {"A": 1154, "C": 2008, "D": "9:52", "I": "eMFw0PKmqnw", "R": 203, "T": 0, "V": "4"}]}, {"H": 6195, "S": 6164, "songs": [{"A": 1154, "C": 2003, "D": "8:31", "I": "qmoy64360YQ", "R": 138, "T": 0, "V": "238"}]}, {"H": 10031, "S": 10031, "songs": [{"A": 1154, "C": 2000, "D": "20:06", "I": "1F7EkcyA3hc", "R": 130, "T": 0, "V": "571"}]}, {"H": 6479, "S": 6478, "songs": [{"A": 1154, "C": 2003, "D": "8:56", "I": "Ns2sZiHAhlg", "R": 123, "T": 0, "V": "13,000"}]}, {"H": 9007, "S": 8803, "songs": [{"A": 1154, "C": 2079, "D": "14:11", "I": "j68H5J6PKXI", "R": 132, "T": 0, "V": "1,000"}, {"A": 1154, "C": 2079, "D": "14:16", "I": "vz4zsfqhq7Y", "R": 132, "T": 0, "V": "360"}]}, {"H": 6037, "S": 6001, "songs": [{"A": 1154, "C": 2014, "D": "3:31", "I": "sb6BQNR7_8o", "R": 100, "T": 0, "V": "2,400"}]}, {"H": 5437, "S": 5429, "songs": [{"A": 1154, "C": 2001, "D": "9:44", "I": "7WOuLDYeazI", "R": 112, "T": 0, "V": "3,500"}]}, {"H": 13191, "S": 12425, "songs": [{"A": 1154, "C": 2020, "D": "3:21", "I": "rjhDB7G7eVI", "R": 306, "T": 0, "V": "312"}]}, {"H": 7043, "S": 6979, "songs": [{"A": 1154, "C": 2003, "D": "6:42", "I": "Of52RllSWUM", "R": 149, "T": 0, "V": "5,864"}]}, {"H": 9415, "S": 9213, "songs": [{"A": 1154, "C": 2003, "D": "8:25", "I": "0UhsdMMjcL4", "R": 183, "T": 0, "V": "259"}]}, {"H": 6093, "S": 6065, "songs": [{"A": 1154, "C": 2003, "D": "15:03", "I": "CogDrZAC5tM", "R": 119, "T": 0, "V": "779"}]}, {"H": 5126, "S": 5123, "songs": [{"A": 1154, "C": 2006, "D": "23:16", "I": "-kwtJS2Mnb0", "R": 114, "T": 0, "V": "10"}, {"A": 1154, "C": 2006, "D": "6:42", "I": "7SufHWrp0dY", "R": 114, "T": 0, "V": "830"}]}, {"H": 6927, "S": 6876, "songs": [{"A": 1154, "C": 2002, "D": "8:56", "I": "2NllAdkkXvs", "R": 151, "T": 0, "V": "330"}]}, {"H": 6721, "S": 6678, "songs": [{"A": 1154, "C": 2003, "D": "5:46", "I": "7Q6BLl4CPMc", "R": 117, "T": 0, "V": "14"}, {"A": 1154, "C": 2003, "D": "7:50", "I": "nxuDdlXZcY8", "R": 117, "T": 0, "V": "6,695"}]}, {"H": 5785, "S": 5769, "songs": [{"A": 1154, "C": 2003, "D": "16:21", "I": "BaEKMQfLa-0", "R": 106, "T": 0, "V": "13"}]}, {"H": 10633, "S": 10299, "songs": [{"A": 1154, "C": 2001, "D": "15:31", "I": "Nh5pZC8tJRQ", "R": 117, "T": 0, "V": "205"}, {"A": 1154, "C": 2001, "D": "16:21", "I": "OsumNX7PFFI", "R": 117, "T": 0, "V": "187"}]}, {"H": 5474, "S": 5471, "songs": [{"A": 1154, "C": 2006, "D": "10:38", "I": "OmY3NIvGhcw", "R": 102, "T": 45, "V": "1,300"}, {"A": 1154, "C": 2006, "D": "10:54", "I": "MVAA9rDL8hg", "R": 102, "T": 45, "V": "11,000"}]}, {"H": 10621, "S": 10286, "songs": [{"A": 1154, "C": 2002, "D": "39:16", "I": "Yc1FZz3yGx4", "R": 104, "T": 0, "V": "261"}]}, {"H": 7872, "S": 7871, "songs": [{"A": 1154, "C": 2008, "D": "9:21", "I": "3VTN9857la4", "R": 124, "T": 0, "V": "189"}]}, {"H": 8085, "S": 7987, "songs": [{"A": 1154, "C": 2003, "D": "19:16", "I": "xmW54Mwb2bg", "R": 153, "T": 0, "V": "209"}]}, {"H": 8330, "S": 8186, "songs": [{"A": 1154, "C": 2003, "D": "7:06", "I": "IkD47XgZPTc", "R": 236, "T": 0, "V": "318"}]}, {"H": 7308, "S": 7229, "songs": [{"A": 1154, "C": 2003, "D": "5:06", "I": "q8nDtCsJ0eI", "R": 101, "T": 0, "V": "330"}]}, {"H": 7649, "S": 7559, "songs": [{"A": 1154, "C": 2003, "D": "7:06", "I": "jL9kZb0KKCc", "R": 173, "T": 0, "V": "694"}]}, {"H": 5861, "S": 5837, "songs": [{"A": 1154, "C": 2003, "D": "28:26", "I": "bFl_yfhoR0s", "R": 112, "T": 37, "V": "16"}]}, {"H": 9925, "S": 9599, "songs": [{"A": 1154, "C": 2003, "D": "10:04", "I": "qKOPsbaE4t8", "R": 140, "T": 0, "V": "1,200"}, {"A": 1154, "C": 2003, "D": "7:51", "I": "ISsB83hv58A", "R": 140, "T": 0, "V": "106"}]}, {"H": 11609, "S": 10996, "songs": [{"A": 1154, "C": 2003, "D": "10:56", "I": "fKQseSdhnjw", "R": 117, "T": 0, "V": "238"}]}, {"H": 5135, "S": 5132, "songs": [{"A": 1154, "C": 2002, "D": "8:44", "I": "HUksiM2ruKs", "R": 120, "T": 25, "V": "2,200"}]}, {"H": 9365, "S": 9174, "songs": [{"A": 1154, "C": 2004, "D": "15:15", "I": "wLOi6Bu81kY", "R": 111, "T": 0, "V": "1,400"}]}, {"H": 5460, "S": 5451, "songs": [{"A": 1154, "C": 2003, "D": "5:05", "I": "jmHntKzP7UQ", "R": 122, "T": 0, "V": "247"}]}, {"H": 11483, "S": 11483, "songs": [{"A": 1154, "C": 2201, "D": "18:56", "I": "BvDcAq0_3aI", "R": 116, "T": 0, "V": "685"}]}, {"H": 5326, "S": 5327, "songs": [{"A": 1154, "C": 2002, "D": "53:01", "I": "wza20m8g2LI", "R": 102, "T": 0, "V": "309"}]}, {"H": 5140, "S": 5142, "songs": [{"A": 1154, "C": 2002, "D": "11:28", "I": "XaWtE2niEio", "R": 160, "T": 25, "V": "833"}]}, {"H": 8929, "S": 8929, "songs": [{"A": 1154, "C": 2261, "D": "16:31", "I": "MN2eIZe5oIE", "R": 136, "T": 0, "V": "1,300"}]}, {"H": 5287, "S": 5281, "songs": [{"A": 1154, "C": 2002, "D": "16:56", "I": "Mk6vuzRiWcc", "R": 153, "T": 0, "V": "198"}]}, {"H": 6802, "S": 6751, "songs": [{"A": 1154, "C": 2004, "D": "5:53", "I": "oIKEfAKxXOQ", "R": 102, "T": 0, "V": "3,700"}]}, {"H": 8920, "S": 8751, "songs": [{"A": 1154, "C": 2003, "D": "5:11", "I": "SqO9LaBZctg", "R": 186, "T": 31, "V": "369"}]}, {"H": 9822, "S": 9567, "songs": [{"A": 1154, "C": 2020, "D": "4:41", "I": "tEd27dJwXOY", "R": 126, "T": 0, "V": "143"}]}, {"H": 9810, "S": 9810, "songs": [{"A": 1154, "C": 2079, "D": "13:06", "I": "3Rv3eK3lo5M", "R": 102, "T": 0, "V": "201"}, {"A": 1154, "C": 2079, "D": "12:41", "I": "AnyXsaq0JHY", "R": 102, "T": 0, "V": "118"}]}, {"H": 11367, "S": 10898, "songs": [{"A": 1154, "C": 2020, "D": "6:06", "I": "WtoN7Lryr8Q", "R": 101, "T": 0, "V": "268"}]}, {"H": 5015, "S": 5014, "songs": [{"A": 1154, "C": 2002, "D": "57:49", "I": "mB6p4PqiC_Y", "R": 108, "T": 25, "V": "89"}]}, {"H": 21, "S": 21, "songs": [{"A": 1154, "C": 2000, "D": "1:10:49", "I": "fo2Zrfh9Pcc", "R": 100, "T": 0, "V": "759"}, {"A": 1154, "C": 2000, "D": "2:38:31", "I": "Sz1B50TWIrk", "R": 100, "T": 0, "V": "61"}]}, {"H": 26, "S": 26, "songs": [{"A": 1154, "C": 2000, "D": "8:02", "I": "Ka7H8DngPNw", "R": 102, "T": 0, "V": "2,800"}]}, {"H": 22, "S": 22, "songs": [{"A": 1154, "C": 2000, "D": "8:06", "I": "p2-pahYWzSc", "R": 123, "T": 0, "V": "1,500"}, {"A": 1154, "C": 2003, "D": "11:13", "I": "oRlbLJiAPmA", "R": 104, "T": 0, "V": "637"}, {"A": 1154, "C": 2000, "D": "21:27", "I": "ifaxQkW6FTY", "R": 102, "T": 0, "V": "2,900"}]}, {"H": 28, "S": 28, "songs": [{"A": 1154, "C": 2000, "D": "3:34", "I": "O-fiLCRWV6Y", "R": 113, "T": 0, "V": "1,300"}]}, {"H": 71, "S": 71, "songs": [{"A": 1154, "C": 2000, "D": "5:42", "I": "JIpufcsNdY0", "R": 100, "T": 0, "V": "4,700"}, {"A": 1154, "C": 2000, "D": "18:36", "I": "4h57OCVybBs", "R": 100, "T": 0, "V": "2,600"}]}, {"H": 5000, "S": 5000, "songs": [{"A": 1154, "C": 2000, "D": "8:51", "I": "JpptInIhkj0", "R": 100, "T": 0, "V": "10,000"}, {"A": 1154, "C": 2000, "D": "0:53", "I": "1nwbJdoLYWo", "R": 100, "T": 0, "V": "1,500"}, {"A": 1154, "C": 2000, "D": "8:32", "I": "IxuTCEl1Soc", "R": 100, "T": 0, "V": "448"}, {"A": 1154, "C": 2000, "D": "9:53", "I": "ztekY0MqLfc", "R": 100, "T": 0, "V": "7,900"}, {"A": 1154, "C": 2000, "D": "8:13", "I": "N-kULsbNuiw", "R": 100, "T": 0, "V": "7"}, {"A": 1154, "C": 2000, "D": "3:46", "I": "NXAp8kSeUwM", "R": 100, "T": 0, "V": "6"}, {"A": 1154, "C": 2000, "D": "59:06", "I": "zH7S7x356CE", "R": 100, "T": 0, "V": "60"}, {"A": 1154, "C": 2000, "D": "24:51", "I": "Gxs6EYFvgbY", "R": 100, "T": 0, "V": "517"}, {"A": 1154, "C": 2000, "D": "37:35", "I": "Sq7W4lzswEk", "R": 100, "T": 0, "V": "101"}, {"A": 1154, "C": 2000, "D": "7:54", "I": "iz8TG_B95zs", "R": 100, "T": 0, "V": "3,500"}, {"A": 1154, "C": 2000, "D": "58:43", "I": "zgTSl3jLQdc", "R": 100, "T": 0, "V": "1,400"}, {"A": 1154, "C": 2000, "D": "4:29", "I": "iM9YH0RGGto", "R": 100, "T": 0, "V": "67"}, {"A": 1154, "C": 2000, "D": "5:08", "I": "A2UKpIBKnyM", "R": 100, "T": 0, "V": "122"}, {"A": 1154, "C": 2000, "D": "2:49", "I": "t5BYVYPDDII", "R": 100, "T": 0, "V": "162"}, {"A": 1154, "C": 2000, "D": "7:13", "I": "z7xyvP98dpk", "R": 100, "T": 0, "V": "90"}, {"A": 1154, "C": 2000, "D": "2:12", "I": "AB9f7mJf5TY", "R": 100, "T": 0, "V": "577"}, {"A": 1154, "C": 2000, "D": "1:05", "I": "hzpx_nlVb_8", "R": 100, "T": 0, "V": "202"}, {"A": 1154, "C": 2000, "D": "1:34", "I": "9CTtHRzxDEI", "R": 100, "T": 0, "V": "690"}, {"A": 1154, "C": 2000, "D": "3:46", "I": "eEavfzFsea0", "R": 100, "T": 0, "V": "373"}, {"A": 1154, "C": 2000, "D": "3:46", "I": "B6gfImbtwPs", "R": 100, "T": 0, "V": "47"}, {"A": 1154, "C": 2000, "D": "11:07", "I": "QajPUGXZBeQ", "R": 100, "T": 0, "V": "655"}, {"A": 1154, "C": 2000, "D": "0:30", "I": "FFNHhTJMLgM", "R": 100, "T": 0, "V": "179"}, {"A": 1154, "C": 2000, "D": "2:55", "I": "MKNzGHoSIGw", "R": 100, "T": 0, "V": "4,600"}, {"A": 1154, "C": 2000, "D": "9:22", "I": "2L2EJ7qGrAY", "R": 100, "T": 0, "V": "5,600"}, {"A": 1154, "C": 2000, "D": "0:09", "I": "cURBFWVb3mM", "R": 100, "T": 0, "V": "645"}, {"A": 1154, "C": 2000, "D": "6:32", "I": "AHo2Z5c8LEk", "R": 100, "T": 0, "V": "2,700"}, {"A": 1154, "C": 2000, "D": "2:56", "I": "0gQJAF_8Vk4", "R": 100, "T": 0, "V": "1,900"}, {"A": 1154, "C": 2000, "D": "5:05", "I": "uNAZn5mK4QY", "R": 100, "T": 0, "V": "980"}, {"A": 1154, "C": 2000, "D": "0:39", "I": "-2JG0UvfsQk", "R": 100, "T": 0, "V": "178"}, {"A": 1154, "C": 2000, "D": "0:20", "I": "iivX7-VNGqI", "R": 100, "T": 0, "V": "714"}, {"A": 1154, "C": 2000, "D": "5:28", "I": "dQa0kfgYzNo", "R": 100, "T": 0, "V": "5,696"}, {"A": 1154, "C": 2000, "D": "7:37", "I": "g7kjsf3FAc4", "R": 100, "T": 0, "V": "3,422"}, {"A": 1154, "C": 2000, "D": "9:27", "I": "x6srgUBf_2Y", "R": 100, "T": 0, "V": "989"}]}]}]}