{"stats": [{"H": "Videos", "C": "102"}, {"H": "Songs", "C": "45"}, {"H": "Ragas", "C": "34"}, {"H": "Composers", "C": "19"}, {"H": "Duration", "C": "14 H"}, {"H": "Views", "C": "9 M"}], "poster": {"P": "Images/VALAYAPATTI.jpg"}, "info": [{"H": "Born", "V": 1940}], "title": {"H": "Valayapatti A. R. Subramaniam", "V": "valaiyappaTTi E. Ar. subramaNiyam", "I": "person-fill"}, "videos": [{"folder": [{"S": 57, "songs": [{"A": 235, "C": 1, "D": "6:23", "I": "ZH7hQVHszHQ", "R": 120, "T": 0, "V": "422"}]}, {"S": 44, "songs": [{"A": 235, "C": 29, "D": "6:28", "I": "UP2GVwwkmOw", "R": 1, "T": 0, "V": "1,044"}]}, {"S": 23, "songs": [{"A": 235, "C": 10, "D": "6:04", "I": "E5Dliktt6pc", "R": 16, "T": 0, "V": "2,735"}]}, {"S": 7, "songs": [{"A": 235, "C": 1, "D": "11:12", "I": "qZMoC_X4OvQ", "R": 7, "T": 0, "V": "1,376"}]}, {"S": 39, "songs": [{"A": 235, "C": 20, "D": "7:50", "I": "g3jPV1JxMS0", "R": 1, "T": 0, "V": "11,295"}]}, {"S": 141, "songs": [{"A": 235, "C": 4, "D": "4:57", "I": "kAw6kYVrW5o", "R": 13, "T": 0, "V": "3,104"}]}, {"S": 43, "songs": [{"A": 235, "C": 12, "D": "3:21", "I": "LydNUcL6wWs", "R": 65, "T": 0, "V": "1,021"}, {"A": 235, "C": 12, "D": "3:32", "I": "I0XE2Gt7bkI", "R": 65, "T": 0, "V": "650"}]}, {"S": 900, "songs": [{"A": 235, "C": 6, "D": "5:35", "I": "ogK66vUSSMs", "R": 0, "T": 0, "V": "38"}]}, {"S": 102, "songs": [{"A": 235, "C": 11, "D": "2:06", "I": "y4gRNZOMUBc", "R": 5, "T": 0, "V": "5,330"}]}, {"S": 5, "songs": [{"A": 235, "C": 6, "D": "4:29", "I": "hYIAdJoLa_g", "R": 230, "T": 0, "V": "1,625"}]}, {"S": 430, "songs": [{"A": 235, "C": 11, "D": "3:46", "I": "1t3GaWm27ks", "R": 86, "T": 0, "V": "428"}]}, {"S": 4, "songs": [{"A": 235, "C": 42, "D": "6:01", "I": "pSJOsvxG0G0", "R": 41, "T": 0, "V": "1,689"}]}, {"S": 129, "songs": [{"A": 235, "C": 1, "D": "28:21", "I": "in66NSN_tJI", "R": 48, "T": 0, "V": "361"}]}, {"S": 83, "songs": [{"A": 235, "C": 2, "D": "14:42", "I": "_zCgTPJcIj4", "R": 2, "T": 21, "V": "387"}]}, {"S": 1306, "songs": [{"A": 235, "C": 9, "D": "4:25", "I": "8wuDIHlBGS0", "R": 326, "T": 0, "V": "156"}]}, {"S": 454, "songs": [{"A": 235, "C": 0, "D": "5:52", "I": "8skSYFQZwS4", "R": 88, "T": 0, "V": "9,223"}, {"A": 235, "C": 0, "D": "7:59", "I": "GcjLE3HWtek", "R": 88, "T": 0, "V": "3,972"}]}, {"S": 318, "songs": [{"A": 235, "C": 0, "D": "15:15", "I": "sl7xSuZIaOs", "R": 104, "T": 0, "V": "534,000"}, {"A": 235, "C": 0, "D": "8:57", "I": "ZXWYejgaTOY", "R": 104, "T": 0, "V": "35,357"}, {"A": 235, "C": 0, "D": "5:27", "I": "hTFdAqmQFTs", "R": 104, "T": 0, "V": "8,653"}, {"A": 235, "C": 0, "D": "12:25", "I": "SBqO-IcF90E", "R": 104, "T": 0, "V": "3,542"}, {"A": 235, "C": 0, "D": "8:14", "I": "-xVwmFRtk3M", "R": 104, "T": 0, "V": "2,930"}, {"A": 235, "C": 0, "D": "4:54", "I": "mFNjAz69h40", "R": 104, "T": 0, "V": "1,135"}]}, {"S": 48, "songs": [{"A": 235, "C": 21, "D": "3:28", "I": "q_oy_-msG_A", "R": 45, "T": 0, "V": "2,255"}]}, {"S": 1141, "songs": [{"A": 235, "C": 15, "D": "4:16", "I": "caidV7Pw2Yo", "R": 15, "T": 12, "V": "351"}]}, {"S": 6, "songs": [{"A": 235, "C": 1, "D": "6:03", "I": "JfimaZagzMQ", "R": 47, "T": 0, "V": "51,492"}, {"A": 235, "C": 1, "D": "12:25", "I": "0IOQlqxk7H4", "R": 47, "T": 0, "V": "6,086"}]}, {"S": 89, "songs": [{"A": 235, "C": 1, "D": "20:23", "I": "hUSPJXnGvLE", "R": 123, "T": 0, "V": "27,331"}]}, {"S": 368, "songs": [{"A": 235, "C": 4, "D": "3:25", "I": "xCCzEKpUZm0", "R": 29, "T": 0, "V": "2,849"}]}, {"S": 104, "songs": [{"A": 235, "C": 21, "D": "4:31", "I": "6VsBPObIMaI", "R": 0, "T": 0, "V": "2,098"}]}, {"S": 8, "songs": [{"A": 235, "C": 9, "D": "10:06", "I": "z6czCGYciPI", "R": 92, "T": 0, "V": "185,000"}, {"A": 235, "C": 9, "D": "21:03", "I": "poCFI-UM6lk", "R": 92, "T": 0, "V": "37,536"}, {"A": 235, "C": 9, "D": "6:41", "I": "9Jsxum9-g0w", "R": 92, "T": 0, "V": "563"}]}, {"S": 167, "songs": [{"A": 235, "C": 1, "D": "5:50", "I": "gRt1tSF5vSk", "R": 153, "T": 0, "V": "329"}]}, {"S": 105, "songs": [{"A": 235, "C": 1, "D": "6:08", "I": "NAICSTny-UE", "R": 73, "T": 0, "V": "273"}]}, {"S": 3, "songs": [{"A": 235, "C": 1, "D": "6:53", "I": "4pEVmMQOqcs", "R": 19, "T": 0, "V": "4,432"}]}, {"S": 374, "songs": [{"A": 235, "C": 6, "D": "26:17", "I": "uCApw8yTbCI", "R": 31, "T": 0, "V": "2,684"}]}, {"S": 192, "songs": [{"A": 235, "C": 52, "D": "4:57", "I": "z_Q9JAHRhxY", "R": 23, "T": 0, "V": "1,366"}, {"A": 235, "C": 52, "D": "4:55", "I": "tT_NgkY2jx8", "R": 23, "T": 0, "V": "431"}]}, {"S": 840, "songs": [{"A": 235, "C": 20, "D": "5:29", "I": "bAYxnr3tq4o", "R": 0, "T": 0, "V": "1,285"}]}, {"S": 3700, "songs": [{"A": 235, "C": 5, "D": "5:21", "I": "YPtsGI33ARM", "R": 0, "T": 0, "V": "328"}]}, {"S": 487, "songs": [{"A": 235, "C": 1, "D": "12:15", "I": "ieKVrmudCRU", "R": 6, "T": 0, "V": "260"}]}, {"S": 576, "songs": [{"A": 235, "C": 182, "D": "5:06", "I": "5InBAfONjHU", "R": 336, "T": 0, "V": "3,147"}]}, {"S": 20, "songs": [{"A": 235, "C": 13, "D": "9:38", "I": "AK4iH9jkGU8", "R": 3, "T": 0, "V": "3,819"}]}, {"S": 20096, "songs": [{"A": 235, "C": 0, "D": "12:28", "I": "Pg3k_Hohx9A", "R": 0, "T": 5, "V": "2,826"}, {"A": 235, "C": 0, "D": "4:13", "I": "wD8I-eoNh8g", "R": 0, "T": 5, "V": "1,629"}]}, {"S": 646, "songs": [{"A": 235, "C": 67, "D": "6:14", "I": "W5Ypcnk24cI", "R": 22, "T": 0, "V": "937"}]}, {"S": 78, "songs": [{"A": 235, "C": 2, "D": "2:40", "I": "DsFIwtppZG8", "R": 22, "T": 6, "V": "654"}]}, {"S": 271, "songs": [{"A": 235, "C": 1, "D": "9:24", "I": "3iY0wkmTubI", "R": 28, "T": 0, "V": "3,321"}]}, {"S": 269, "songs": [{"A": 235, "C": 1, "D": "5:20", "I": "DlEpms4__ok", "R": 2, "T": 0, "V": "889"}]}, {"S": 1, "songs": [{"A": 235, "C": 2, "D": "10:49", "I": "uOYXy7A0tOc", "R": 11, "T": 6, "V": "3,655,427"}, {"A": 235, "C": 2, "D": "15:14", "I": "_BfpxxGi9yI", "R": 11, "T": 6, "V": "7,720"}]}, {"S": 20110, "songs": [{"A": 235, "C": 0, "D": "4:52", "I": "933pMUkgtVQ", "R": 0, "T": 0, "V": "808"}]}, {"S": 20058, "songs": [{"A": 235, "C": 0, "D": "23:39", "I": "J5dwWRFd8f4", "R": 47, "T": 0, "V": "1,744,680"}, {"A": 235, "C": 0, "D": "2:25", "I": "sKM1rJLdKEE", "R": 230, "T": 0, "V": "4,522"}, {"A": 235, "C": 0, "D": "5:45", "I": "hMyh6zBzW10", "R": 6, "T": 0, "V": "803"}, {"A": 235, "C": 0, "D": "31:15", "I": "Nr0IKzoEwck", "R": 7, "T": 0, "V": "2,078"}, {"A": 235, "C": 0, "D": "8:00", "I": "V6ZyUL4nxOU", "R": 43, "T": 0, "V": "3,303"}, {"A": 235, "C": 0, "D": "2:25", "I": "YpPs1YuMvDI", "R": 153, "T": 0, "V": "301"}, {"A": 235, "C": 0, "D": "1:15", "I": "jwPlDfByx1E", "R": 326, "T": 0, "V": "132"}, {"A": 235, "C": 0, "D": "7:30", "I": "TtQZQ5mToTI", "R": 3, "T": 0, "V": "1,199"}, {"A": 235, "C": 0, "D": "1:10", "I": "w6Y142yiGzU", "R": 3, "T": 0, "V": "117"}]}, {"S": 20897, "songs": [{"A": 235, "C": 0, "D": "1:09:17", "I": "qkodWqsMIBE", "R": 0, "T": 0, "V": "1,028"}]}, {"S": 20055, "songs": [{"A": 235, "C": 0, "D": "1:06:06", "I": "yMf3-wQwIyQ", "R": 0, "T": 0, "V": "673,032"}, {"A": 235, "C": 0, "D": "6:58", "I": "lLgJsiI0JzQ", "R": 0, "T": 0, "V": "136,609"}, {"A": 235, "C": 0, "D": "9:26", "I": "psQDiNyCSSA", "R": 0, "T": 0, "V": "127,891"}, {"A": 235, "C": 0, "D": "6:18", "I": "Lmz_MzmCl2s", "R": 0, "T": 0, "V": "8,137"}, {"A": 235, "C": 0, "D": "8:41", "I": "3V5VYkJ02Mo", "R": 0, "T": 0, "V": "3,484"}, {"A": 235, "C": 0, "D": "11:49", "I": "ZvOZ2jmFWo4", "R": 0, "T": 0, "V": "1,099"}]}, {"S": 0, "songs": [{"A": 235, "C": 0, "D": "8:17", "I": "mzpgwO-i_H4", "R": 0, "T": 0, "V": "269,832"}, {"A": 235, "C": 0, "D": "10:32", "I": "Ql_8OMH43q8", "R": 0, "T": 0, "V": "164,398"}, {"A": 235, "C": 0, "D": "5:42", "I": "4GW7-sBEnk4", "R": 0, "T": 0, "V": "147,000"}, {"A": 235, "C": 0, "D": "4:34", "I": "yhhI2wA76kQ", "R": 0, "T": 0, "V": "116,707"}, {"A": 235, "C": 0, "D": "14:35", "I": "UxdgsLIeQDA", "R": 0, "T": 0, "V": "55,709"}, {"A": 235, "C": 0, "D": "9:53", "I": "YnuIcN6uus0", "R": 0, "T": 0, "V": "27,619"}, {"A": 235, "C": 0, "D": "9:47", "I": "emAEjvcg9Nk", "R": 0, "T": 0, "V": "12,499"}, {"A": 235, "C": 0, "D": "10:25", "I": "bomdL_JJPW4", "R": 0, "T": 0, "V": "6,013"}, {"A": 235, "C": 0, "D": "4:24", "I": "ykCr9r9Qx_I", "R": 0, "T": 0, "V": "3,405"}, {"A": 235, "C": 0, "D": "12:43", "I": "NVsCsPg3tDA", "R": 0, "T": 0, "V": "3,133"}, {"A": 235, "C": 0, "D": "7:57", "I": "NoCArOu-2-c", "R": 0, "T": 0, "V": "2,903"}, {"A": 235, "C": 0, "D": "3:11", "I": "q2w3aLTW7x8", "R": 0, "T": 0, "V": "2,755"}, {"A": 235, "C": 0, "D": "5:32", "I": "qsIaBjwUask", "R": 0, "T": 0, "V": "2,568"}, {"A": 235, "C": 0, "D": "6:55", "I": "_8kZhmf3RC0", "R": 0, "T": 0, "V": "2,160"}, {"A": 235, "C": 0, "D": "7:24", "I": "OA8jRHR7rfY", "R": 0, "T": 0, "V": "1,955"}, {"A": 235, "C": 0, "D": "7:38", "I": "NmtSJh_RPS0", "R": 0, "T": 0, "V": "1,640"}, {"A": 235, "C": 0, "D": "11:38", "I": "tOwtR1DnoK0", "R": 0, "T": 0, "V": "1,631"}, {"A": 235, "C": 0, "D": "9:01", "I": "uyMeBtkDL1g", "R": 0, "T": 0, "V": "1,394"}, {"A": 235, "C": 0, "D": "5:50", "I": "TpGnn6Izjas", "R": 0, "T": 0, "V": "1,199"}, {"A": 235, "C": 0, "D": "4:38", "I": "VmcsmTs19ek", "R": 0, "T": 0, "V": "1,178"}, {"A": 235, "C": 0, "D": "5:22", "I": "3ch-w-ftGcM", "R": 0, "T": 0, "V": "969"}, {"A": 235, "C": 0, "D": "7:55", "I": "8SoOQWTKvBU", "R": 0, "T": 0, "V": "948"}, {"A": 235, "C": 0, "D": "6:57", "I": "rCJLqOproT0", "R": 0, "T": 0, "V": "893"}, {"A": 235, "C": 0, "D": "5:51", "I": "ukDWS-j13a0", "R": 0, "T": 0, "V": "880"}, {"A": 235, "C": 0, "D": "8:37", "I": "n8MgvCY_b5M", "R": 0, "T": 0, "V": "666"}, {"A": 235, "C": 0, "D": "3:51", "I": "2DqKlJE__rs", "R": 0, "T": 0, "V": "629"}, {"A": 235, "C": 0, "D": "3:42", "I": "mFT-SlV1Dlc", "R": 0, "T": 0, "V": "605"}, {"A": 235, "C": 0, "D": "6:49", "I": "NSmLgVAPd5s", "R": 0, "T": 0, "V": "216"}, {"A": 235, "C": 0, "D": "2:44", "I": "RlQCc7TSEsQ", "R": 0, "T": 0, "V": "193"}, {"A": 235, "C": 0, "D": "3:46", "I": "XizzuuMAS6A", "R": 0, "T": 0, "V": "129"}, {"A": 235, "C": 0, "D": "6:52", "I": "3m9nAcwY-uQ", "R": 0, "T": 0, "V": "113"}, {"A": 235, "C": 0, "D": "12:43", "I": "50zfk2DWsEE", "R": 0, "T": 0, "V": "6"}]}]}]}