{"stats": [{"H": "Videos", "C": "2"}, {"H": "Ragas", "C": "1"}, {"H": "Artists", "C": "1"}, {"H": "Types", "C": "1"}, {"H": "Duration", "C": "10 M"}, {"H": "Views", "C": "387"}], "info": [{"H": "Type", "V": "Varnam", "P": "varNam", "I": 4}, {"H": "Composer", "V": "S. Ramanathan", "P": "es. rAma.NAthan", "I": 2055}, {"H": "Raga", "V": "Behag", "P": "bihAg", "I": 20}, {"H": "Tala", "V": "Adi", "P": "Adi", "I": 1}, {"H": "Tala name", "V": "Chatusra Jaati Triputa Tala", "P": "chatuSra jAti tripuTa tALA", "I": 0}, {"H": "Tala angas", "V": "Laghu-1, Dhruta-2", "P": "laghu-1, d.RtA-2", "I": 0}, {"H": "Tala count", "V": "4 + 2 + 2 = 8", "P": "4 + 2 + 2 = 8", "I": 0}, {"H": "Language", "V": "Tamil", "P": "Tamil", "I": 0}], "title": {"T": 5482, "H": "Angayarkanniye", "V": "aMgayaRkaNNiyE", "I": "music-note-beamed"}, "songs": [{"I": "JRrRXL6Cy_k&start=2624&end=2905", "T": 4, "S": 5482, "R": 20, "C": 2055, "A": 383, "D": "4:41", "V": "441", "J": "m"}, {"I": "6U3MpRnzcoc", "T": 4, "S": 5482, "R": 20, "C": 2055, "A": 383, "D": "6:35", "V": "387", "J": "m"}], "folders": [["artist", 383, "0,1"]], "languages": {"english": "0", "tamil": "0", "telugu": "0", "kannada": "0", "malayalam": "0", "hindi": "0", "marathi": "0", "bengali": "0", "gujarati": "0", "punjabi": "0", "odia": "0", "assamese": "0"}}