{"stats": [{"H": "Videos", "C": "1"}, {"H": "Ragas", "C": "1"}, {"H": "Artists", "C": "1"}, {"H": "Types", "C": "1"}, {"H": "Duration", "C": "7 M"}, {"H": "Views", "C": "205"}], "info": [{"H": "Type", "V": "Krithi", "P": "k.Rti"}, {"H": "Composer", "V": "Annamacharya", "P": "annamAcAryA"}, {"H": "Raga", "V": "Unknownraga", "P": "?"}], "title": {"H": "Daivama O Daivama", "V": "daivamA O daivamA", "I": "music-note-beamed"}, "videos": [{"folder": [{"A": 32, "songs": [{"C": 7, "D": "7:11", "I": "qApI8mFabYI", "J": "h", "R": 0, "S": 8103, "T": 0, "V": "205"}]}]}], "songs": [{"I": "qApI8mFabYI", "T": 0, "S": 8103, "R": 0, "C": 7, "A": 32, "D": "7:11", "V": "205", "J": "h"}], "folders": [["artist", 32, "0"]], "languages": {"english": "0", "tamil": "0", "telugu": "0", "kannada": "0", "malayalam": "0", "hindi": "0", "marathi": "0", "bengali": "0", "gujarati": "0", "punjabi": "0", "odia": "0", "assamese": "0"}}