{"stats": [{"H": "Videos", "C": "1"}, {"H": "Ragas", "C": "1"}, {"H": "Artists", "C": "1"}, {"H": "Types", "C": "1"}, {"H": "Duration", "C": "7 M"}, {"H": "Views", "C": "546"}], "info": [{"H": "Type", "V": "Krithi", "P": "kiruthi"}, {"H": "Composer", "V": "Chitravina Ravikiran", "P": "chitthiravINA ravikiran"}, {"H": "Raga", "V": "Suruti", "P": "suruTTi"}, {"H": "Tala", "V": "Rupaka", "P": "rupaka"}, {"H": "Tala name", "V": "Chatusra Jaati Rupaka Tala", "P": "chatuSra jAti rupaka tALA"}, {"H": "Tala angas", "V": "Dhruta-1, Laghu-1", "P": "Dhruta-1, Laghu-1"}, {"H": "Tala count", "V": "2 + 4 = 6", "P": "2 + 4 = 6"}, {"H": "Language", "V": "Tamil", "P": "Tamil"}], "title": {"H": "Mummoortihalai Panivai", "V": "Mummoortihalai Panivai", "I": "music-note-beamed"}, "videos": [{"folder": [{"A": [3795, 3124], "songs": [{"C": [3688, 3032], "D": "7:17", "I": "PviMWjyNsA0", "R": [1650, 1032], "S": [16156, 16156], "T": [0, 0], "V": "546"}]}]}]}