{"stats": [{"H": "Videos", "C": "9"}, {"H": "Ragas", "C": "1"}, {"H": "Artists", "C": "5"}, {"H": "Types", "C": "1"}, {"H": "Duration", "C": "29 M"}, {"H": "Views", "C": "21 K"}], "info": [{"H": "Type", "V": "Krithi", "P": "k.Rti"}, {"H": "Composer", "V": "UnknownComposer", "P": "?"}, {"H": "Raga", "V": "Unknownraga", "P": "?"}], "title": {"H": "Pulli Kalapam", "V": "pulli kalapam", "I": "music-note-beamed"}, "videos": [{"folder": [{"A": 13, "songs": [{"C": 0, "D": "4:08", "I": "cPpGF-Q4_6M&start=3327&end=3575", "J": "m", "R": 0, "S": 2827, "T": 0, "V": "787,755"}, {"C": 0, "D": "4:09", "I": "XTM0RFnLUjI", "J": "m", "R": 0, "S": 2827, "T": 0, "V": "16,022"}, {"C": 0, "D": "4:08", "I": "0AZT4NY08ms&start=3327&end=3575", "J": "h", "R": 0, "S": 2827, "T": 0, "V": "276"}]}, {"A": 116, "songs": [{"C": 0, "D": "4:46", "I": "NQgkKmJfcgU&start=4021&end=4307", "J": "h", "R": 0, "S": 2827, "T": 0, "V": "57,842"}]}, {"A": 38, "songs": [{"C": 0, "D": "2:22", "I": "LYOtl47gVbE&start=4058&end=4200", "J": "m", "R": 0, "S": 2827, "T": 0, "V": "13,614"}, {"C": 0, "D": "2:24", "I": "vvTmOg3d6KA", "J": "m", "R": 0, "S": 2827, "T": 0, "V": "790"}]}, {"A": 5, "songs": [{"C": 0, "D": "3:01", "I": "_6tBnJ83How", "J": "m", "R": 0, "S": 2827, "T": 0, "V": "2,356"}, {"C": 0, "D": "3:49", "I": "QMM7C8KHiA4", "J": "m", "R": 0, "S": 2827, "T": 0, "V": "1,653"}]}, {"A": 595, "songs": [{"C": 0, "D": "3:06", "I": "b4VcmyJIH7Y", "J": "m", "R": 0, "S": 2827, "T": 0, "V": "179"}]}]}], "songs": [{"I": "cPpGF-Q4_6M&start=3327&end=3575", "T": 0, "S": 2827, "R": 0, "C": 0, "A": 13, "D": "4:08", "V": "787,755", "J": "m"}, {"I": "XTM0RFnLUjI", "T": 0, "S": 2827, "R": 0, "C": 0, "A": 13, "D": "4:09", "V": "16,022", "J": "m"}, {"I": "0AZT4NY08ms&start=3327&end=3575", "T": 0, "S": 2827, "R": 0, "C": 0, "A": 13, "D": "4:08", "V": "276", "J": "h"}, {"I": "NQgkKmJfcgU&start=4021&end=4307", "T": 0, "S": 2827, "R": 0, "C": 0, "A": 116, "D": "4:46", "V": "57,842", "J": "h"}, {"I": "LYOtl47gVbE&start=4058&end=4200", "T": 0, "S": 2827, "R": 0, "C": 0, "A": 38, "D": "2:22", "V": "13,614", "J": "m"}, {"I": "vvTmOg3d6KA", "T": 0, "S": 2827, "R": 0, "C": 0, "A": 38, "D": "2:24", "V": "790", "J": "m"}, {"I": "_6tBnJ83How", "T": 0, "S": 2827, "R": 0, "C": 0, "A": 5, "D": "3:01", "V": "2,356", "J": "m"}, {"I": "QMM7C8KHiA4", "T": 0, "S": 2827, "R": 0, "C": 0, "A": 5, "D": "3:49", "V": "1,653", "J": "m"}, {"I": "b4VcmyJIH7Y", "T": 0, "S": 2827, "R": 0, "C": 0, "A": 595, "D": "3:06", "V": "179", "J": "m"}], "folders": [["artist", 13, "0,1,2"], ["artist", 116, "3"], ["artist", 38, "4,5"], ["artist", 5, "6,7"], ["artist", 595, "8"]], "languages": {"english": "4,0,1,2,3", "tamil": "2,3,0,1,4", "telugu": "0,1,4,2,3", "kannada": "0,1,4,2,3", "malayalam": "0,1,4,2,3", "hindi": "0,1,4,2,3", "marathi": "0,1,4,2,3", "bengali": "0,1,4,2,3", "gujarati": "0,1,4,2,3", "punjabi": "0,1,4,2,3", "odia": "0,1,4,2,3", "assamese": "0,1,4,2,3"}}