{"stats": [{"H": "Videos", "C": "3"}, {"H": "Ragas", "C": "3"}, {"H": "Artists", "C": "1"}, {"H": "Types", "C": "1"}, {"H": "Duration", "C": "27 M"}, {"H": "Views", "C": "3 K"}], "info": [], "title": {"H": "Ragam thanam pallavi - Vishal Sapuram", "V": "rAgaM thAnaM pallavi - vishAl sApuram", "I": "music-note-beamed"}, "videos": [{"folder": [{"A": 3814, "songs": [{"C": 5000, "D": "3:24", "I": "8eWO2mPMNGk", "R": 1166, "S": 40530, "T": 0, "V": "1,010"}, {"C": 5000, "D": "1:28", "I": "ZHdBAaZriZ4", "R": 1060, "S": 40530, "T": 0, "V": "996"}, {"C": 5000, "D": "23:20", "I": "dch5HK2zyN0", "R": 1130, "S": 40530, "T": 0, "V": "293"}]}]}]}