{"stats": [{"H": "Videos", "C": "1"}, {"H": "Songs", "C": "1"}, {"H": "Composers", "C": "1"}, {"H": "Types", "C": "1"}, {"H": "Duration", "C": "1 H"}, {"H": "Views", "C": "87"}], "info": [], "title": {"T": 7231, "H": "Malhar, Gorakh kalyan", "V": "malhAr, gOrakh kalyAN", "I": "music-note-list"}, "songs": [{"I": "g7Ba_007x3U", "T": 0, "S": 20001, "R": 7231, "C": 0, "A": 230, "D": "1:07:28", "V": "87", "J": "m"}], "folders": [["song", 20001, "0"]], "languages": {"english": "0", "tamil": "0", "telugu": "0", "kannada": "0", "malayalam": "0", "hindi": "0", "marathi": "0", "bengali": "0", "gujarati": "0", "punjabi": "0", "odia": "0", "assamese": "0"}}